AUTHORS
CHANGELOG
INSTALL
LICENSE
MANIFEST.in
README.rst
setup.py
django_xross.egg-info/PKG-INFO
django_xross.egg-info/SOURCES.txt
django_xross.egg-info/dependency_links.txt
django_xross.egg-info/not-zip-safe
django_xross.egg-info/top_level.txt
docs/Makefile
docs/source/conf.py
docs/source/index.rst
docs/source/javascript.rst
docs/source/python.rst
docs/source/quickstart.rst
docs/source/rst_guide.rst
xross/__init__.py
xross/exceptions.py
xross/models.py
xross/runtests.py
xross/tests.py
xross/toolbox.py
xross/utils.py
xross/static/js/xross/xross.js
xross/static/js/xross/xross.min.js