Metadata-Version: 1.1
Name: django-xross
Version: 0.6.0
Summary: Reusable application for Django nicely bridging client and server sides.
Home-page: https://github.com/idlesign/django-xross
Author: Igor `idle sign` Starikov
Author-email: idlesign@yandex.ru
License: BSD 3-Clause License
Platform: UNKNOWN
Classifier: Development Status :: 4 - Beta
Classifier: Operating System :: OS Independent
Classifier: Programming Language :: Python
Classifier: Programming Language :: Python :: 3
Classifier: Programming Language :: Python :: 3.3
Classifier: Programming Language :: Python :: 3.4
Classifier: Programming Language :: Python :: 3.5
Classifier: License :: OSI Approved :: BSD License
